solidity_parser/README.md
solidity_parser/__init__.py
solidity_parser/dependencies.py
solidity_parser/grammar.py
solidity_parser/main.py
solidity_parser/nodes.py
py_solidity_ast-0.1.4.dist-info/METADATA
py_solidity_ast-0.1.4.dist-info/WHEEL
py_solidity_ast-0.1.4.dist-info/licenses/LICENSE
py_solidity_ast-0.1.4.dist-info/RECORD
