Metadata-Version: 2.1
Name: py-solidity-ast
Version: 0.1.4
Summary: A Python library for parsing and working with the AST output of the Solc compiler
Project-URL: Homepage, https://github.com/AfroSec-Audits/py-solidity-ast
Author-email: dev0cloo <etor.ocloo@gmail.com>, 0xAfroSec <afrosecaudits@gmail.com>
Maintainer-email: dev0cloo <etor.ocloo@gmail.com>, 0xAfroSec <afrosecaudits@gmail.com>
License: MIT License
License-File: LICENSE
Keywords: AST,parser,solc,solidity
Classifier: License :: OSI Approved :: MIT License
Classifier: Operating System :: OS Independent
Classifier: Programming Language :: Python :: 3
Requires-Python: >=3.9
